searchx/Client.py
searchx/__init__.py
searchx/lib/__init__.py
searchx/lib/objects.py
searchx/lib/settings.py
searchx-1.0.1.dist-info/METADATA
searchx-1.0.1.dist-info/WHEEL
searchx-1.0.1.dist-info/top_level.txt
searchx-1.0.1.dist-info/RECORD
