Metadata-Version: 2.1
Name: searchx
Version: 1.0.1
Summary: SearchX is a powerful library for convenient searching.
Home-page: https://github.com/RedPiarOfficial/searchx/
Author: RedPiar
Author-email: Regeonwix@gmail.com
Keywords: search,google,bing,x,translation,image-search,image
Classifier: Programming Language :: Python :: 3
Classifier: License :: OSI Approved :: MIT License
Classifier: Operating System :: OS Independent
Requires-Python: >=3.8
Requires-Dist: cloudscraper
Requires-Dist: httpx
Requires-Dist: bs4
